README.md
setup.py
redboard/__init__.py
redboard/console.py
redboard.egg-info/PKG-INFO
redboard.egg-info/SOURCES.txt
redboard.egg-info/dependency_links.txt
redboard.egg-info/entry_points.txt
redboard.egg-info/requires.txt
redboard.egg-info/top_level.txt