Metadata-Version: 1.1
Name: redboard
Version: 0.1.5
Summary: Python library to drive the RedBoard+ motor controller
Home-page: https://github.com/ApproxEng/RedBoard
Author: Tom Oinn
Author-email: tomoinn@gmail.com
License: UNKNOWN
Platform: UNKNOWN
Classifier: Programming Language :: Python :: 3.6
